sitetables/__init__.py
sitetables/apps.py
sitetables/exceptions.py
sitetables/settings.py
sitetables/urls.py
sitetables/views.py
sitetables/plugins/__init__.py
sitetables/plugins/base.py
sitetables/plugins/i18n.py
sitetables/plugins/style/__init__.py
sitetables/plugins/style/bootstrap3.py
sitetables/plugins/style/bootstrap4.py
sitetables/plugins/style/foundation.py
sitetables/plugins/style/jqueryui.py
sitetables/plugins/style/semantic.py
sitetables/templatetags/__init__.py
sitetables/templatetags/sitetables.py
sitetables/tests/__init__.py
sitetables/tests/conftest.py
sitetables/tests/test_plugins.py
sitetables/tests/test_sources.py
sitetables/tests/test_tables.py
sitetables/tests/test_tags.py
sitetables/tests/test_views.py
sitetables/tests/testapp/__init__.py
sitetables/tests/testapp/models.py
sitetables/tests/testapp/urls.py
sitetables/toolbox/__init__.py
sitetables/toolbox/columns.py
sitetables/toolbox/sources.py
sitetables/toolbox/tables.py
sitetables/toolbox/utils.py
django_sitetables-0.2.1.dist-info/AUTHORS
django_sitetables-0.2.1.dist-info/LICENSE
django_sitetables-0.2.1.dist-info/METADATA
django_sitetables-0.2.1.dist-info/WHEEL
django_sitetables-0.2.1.dist-info/top_level.txt
django_sitetables-0.2.1.dist-info/RECORD
